acousticspy/__init__.py
acousticspy/absorption/__init__.py
acousticspy/absorption/absorption.py
acousticspy/conversions/__init__.py
acousticspy/conversions/conversions.py
acousticspy/decibels/__init__.py
acousticspy/decibels/decibels.py
acousticspy/metrics/__init__.py
acousticspy/metrics/metrics.py
acousticspy/room/__init__.py
acousticspy/room/room_modes.py
acousticspy/sources/__init__.py
acousticspy/sources/pressure_field.py
acousticspy/sources/source_models.py
acousticspy/spectra/__init__.py
acousticspy/spectra/fft_analysis.py
acousticspy-0.6.2.dist-info/LICENSE
acousticspy-0.6.2.dist-info/METADATA
acousticspy-0.6.2.dist-info/WHEEL
acousticspy-0.6.2.dist-info/top_level.txt
acousticspy-0.6.2.dist-info/RECORD
