Metadata-Version: 2.1
Name: acousticspy
Version: 0.6.2
Summary: Lots of simple acoustics calculations, all in one place.
Home-page: UNKNOWN
Author: Mark C. Anderson
Author-email: anderson.mark.az@gmail.com
License: UNKNOWN
Keywords: python,acoustics
Platform: UNKNOWN
Classifier: Development Status :: 2 - Pre-Alpha
Classifier: Intended Audience :: Science/Research
Classifier: Programming Language :: Python :: 3
Classifier: Operating System :: MacOS :: MacOS X
Classifier: Operating System :: Microsoft :: Windows
Classifier: License :: OSI Approved :: MIT License
Classifier: Topic :: Scientific/Engineering
Classifier: Topic :: Scientific/Engineering :: Physics
Requires-Dist: numpy
Requires-Dist: scipy
Requires-Dist: matplotlib
Requires-Dist: pandas
